datarobot_storage/__init__.py
datarobot_storage/__main__.py
datarobot_storage/amazon.py
datarobot_storage/amazon.pyi
datarobot_storage/azure.py
datarobot_storage/azure.pyi
datarobot_storage/base.py
datarobot_storage/base.pyi
datarobot_storage/enums.py
datarobot_storage/exceptions.py
datarobot_storage/google.py
datarobot_storage/google.pyi
datarobot_storage/helpers.py
datarobot_storage/helpers.pyi
datarobot_storage/put_generator.py
datarobot_storage/py.typed
datarobot_storage/utils/__init__.py
datarobot_storage/utils/async_storage.py
datarobot_storage/utils/dr_libs.py
datarobot_storage/utils/storage.py
datarobot_storage-2.2.0.dist-info/LICENSE
datarobot_storage-2.2.0.dist-info/METADATA
datarobot_storage-2.2.0.dist-info/WHEEL
datarobot_storage-2.2.0.dist-info/RECORD
