Metadata-Version: 2.1
Name: datarobot-storage
Version: 2.2.0
Summary: Reusable storage access for DataRobot
License: DataRobot Tool and Utility Agreement
Author: DataRobot
Author-email: support@datarobot.com
Requires-Python: >=3.9,<4.0
Classifier: License :: Other/Proprietary License
Classifier: Programming Language :: Python :: 3
Classifier: Programming Language :: Python :: 3.9
Classifier: Programming Language :: Python :: 3.10
Classifier: Programming Language :: Python :: 3.11
Requires-Dist: azure-identity (>=1.15.0,<2.0.0)
Requires-Dist: azure-storage-blob (==12.19.0)
Requires-Dist: boto3 (>=1.33.13,<2.0.0)
Requires-Dist: filechunkio (>=1.6,<2.0)
Requires-Dist: google-cloud-storage (>=2.19.0,<3.0.0)
